[
  {
    "id": "686",
    "koreanName": "어둠의 화살",
    "englishName": "Shadow Bolt",
    "icon": "spell_shadow_shadowbolt",
    "description": "적에게 어둠의 화살을 발사하여 (주문력의 70.2%)의 암흑 피해를 입힙니다. [ 악마: 영혼의 조각 1개를 생성합니다.]",
    "cooldown": "해당 없음",
    "castTime": "2 초",
    "resourceCost": "1.5% (기본 마나 중)",
    "resourceGain": "없음",
    "type": "기본",
    "spec": "파괴"
  },
  {
    "id": "104316",
    "koreanName": "공포사냥개 부르기",
    "englishName": "Call Dreadstalkers",
    "icon": "spell_warlock_calldreadstalkers",
    "description": "스킬 설명이 없습니다.",
    "cooldown": "20 초",
    "castTime": "2 초",
    "resourceCost": "영혼의 조각 2개",
    "resourceGain": "없음",
    "type": "기본",
    "spec": "악마"
  },
  {
    "id": "265187",
    "koreanName": "악마 폭군 소환",
    "englishName": "Summon Demonic Tyrant",
    "icon": "inv_summondemonictyrant",
    "description": "악마 폭군을 소환하여 공포사냥개, 썩은마귀, 지옥수호병, 최대 10마리의 날뛰는 임프의 지속시간을 15초만큼 증가시킵니다. 또한 악마 폭군은 대상에게 피해를 입히는 동안 영향을 받는 악마들의 공격력을 25%만큼 증가시킵니다. [영혼결속 폭군: 영혼의 조각 0개를 생성합니다.]",
    "cooldown": "1 분",
    "castTime": "2 초",
    "resourceCost": "2% (기본 마나 중)",
    "resourceGain": "없음",
    "type": "기본",
    "spec": "공용"
  },
  {
    "id": "111898",
    "koreanName": "흑마법서: 지옥수호병",
    "englishName": "Grimoire: Felguard",
    "icon": "spell_shadow_demonicpact",
    "description": "지옥수호병을 소환하여 17초 동안 대상을 공격하여 대상이 입는 피해가 125%만큼 증가합니다.지옥수호병 소환 시 대상의 주문 시전을 방해하고 기절시킵니다.",
    "cooldown": "2 분",
    "castTime": "즉시",
    "resourceCost": "영혼의 조각 1개",
    "resourceGain": "없음",
    "type": "기본",
    "spec": "공용"
  },
  {
    "id": "6353",
    "koreanName": "영혼의 불꽃",
    "englishName": "Soul Fire",
    "icon": "spell_fire_firebolt",
    "description": "적의 영혼을 불태워 (주문력의 476.28%)의 화염 피해를 입히고 제물|1을;를; 부여합니다.영혼의 조각 1개를 생성합니다.",
    "cooldown": "45 초",
    "castTime": "4 초",
    "resourceCost": "2% (기본 마나 중)",
    "resourceGain": "없음",
    "type": "기본",
    "spec": "공용"
  },
  {
    "id": "196277",
    "koreanName": "파열",
    "englishName": "Implosion",
    "icon": "inv_implosion",
    "description": "모든 날뛰는 임프를 악마의 힘으로 대상에게 끌어당긴 후 격렬하게 폭발시켜, 8미터 내의 모든 적에게 (주문력의 54.5531%)의 암흑불길 피해를 입힙니다.",
    "cooldown": "해당 없음",
    "castTime": "즉시",
    "resourceCost": "2% (기본 마나 중)",
    "resourceGain": "없음",
    "type": "기본",
    "spec": "공용"
  },
  {
    "id": "108416",
    "koreanName": "어둠의 서약",
    "englishName": "Dark Pact",
    "icon": "spell_shadow_deathpact",
    "description": "현재 생명력의 20%만큼을 희생시켜, 20초 동안 희생한 생명력의 200%만큼 피해를 흡수하고 추가로 (주문력 * 2.5)의 피해를 흡수하는 보호막을 자신에게 씌웁니다. 제어 방해 효과에 걸린 상태에서도 사용할 수 있습니다.",
    "cooldown": "1 분",
    "castTime": "즉시",
    "resourceCost": "없음",
    "resourceGain": "없음",
    "type": "기본",
    "spec": "악마"
  },
  {
    "id": "386997",
    "koreanName": "영혼 부식",
    "englishName": "Soul Rot",
    "icon": "inv_ability_warlock_soulrot",
    "description": "현재 대상과 주위에 있는 최대 4명의 추가 대상의 생명을 말라붙게 만들어 8초에 걸쳐 주 대상에게는 32의 암흑 피해를, 부가 대상에게는 16의 암흑 피해를 입힙니다.영혼 부식으로 입힌 피해의 50%만큼 생명력을 회복합니다.",
    "cooldown": "1 분",
    "castTime": "1.5 초",
    "resourceCost": "0.5% (기본 마나 중)",
    "resourceGain": "없음",
    "type": "기본",
    "spec": "공용"
  },
  {
    "id": "30146",
    "koreanName": "지옥수호병 소환",
    "englishName": "Summon Felguard",
    "icon": "spell_shadow_summonfelguard",
    "description": "스킬 설명이 없습니다.",
    "cooldown": "해당 없음",
    "castTime": "6 초",
    "resourceCost": "영혼의 조각 1개",
    "resourceGain": "없음",
    "type": "기본",
    "spec": "공용"
  },
  {
    "id": "205180",
    "koreanName": "암흑시선 소환",
    "englishName": "Summon Darkglare",
    "icon": "inv_beholderwarlock",
    "description": "뒤틀린 황천에서 암흑시선을 소환하여 모든 적에 대한 자신의 지속 피해 효과의 지속시간을 8초만큼 연장합니다.암흑시선은 20초 동안 전투를 도우며 대상을 폭발시켜 (주문력의 135.29%)의 암흑 피해를 입히고, 이 피해는 암흑시선의 현재 대상에게 활성화되어 있는 지속 피해 효과 하나당 45%만큼 증가합니다.",
    "cooldown": "2 분",
    "castTime": "즉시",
    "resourceCost": "2% (기본 마나 중)",
    "resourceGain": "없음",
    "type": "기본",
    "spec": "공용"
  },
  {
    "id": "264057",
    "koreanName": "영혼의 일격",
    "englishName": "Soul Strike",
    "icon": "inv_polearm_2h_fellord_04",
    "description": "고통,  파괴지옥수호병에게 적의 영혼을 강타하여 (.575 * (주문력) * (1 + 유연성))의 암흑 피해를 입히도록 명령합니다. 악마지옥수호병에게 적의 영혼을 강타하여 (.575 * (주문력) * 1 * (1 + 유연성))의 암흑 피해를 입히도록 명령합니다.영혼의 조각 1개를 생성합니다.",
    "cooldown": "10 초",
    "castTime": "즉시",
    "resourceCost": "없음",
    "resourceGain": "없음",
    "type": "기본",
    "spec": "공용"
  },
  {
    "id": "264106",
    "koreanName": "죽음의 화살",
    "englishName": "Deathbolt",
    "icon": "spell_fire_twilightflamebolt",
    "description": "대상에게 죽음의 화살을 날려, 대상에게 걸린 주문의 잔여 피해 중 50%에 해당하는 피해를 축적시키고 3초에 걸쳐 입힙니다. [완전한 부패: 최대 14초 동안의 부패 피해가 적용됩니다]",
    "cooldown": "30 초",
    "castTime": "1 초",
    "resourceCost": "영혼의 조각 3개",
    "resourceGain": "없음",
    "type": "기본",
    "spec": "공용"
  }
]